{"GlobalPropertiesHash":"+JpMoEu7kLL/ocrUMjx1oFMVCR3fnFP5RTwswSpuZFs=","FingerprintPatternsHash":"gq3WsqcKBUGTSNle7RKKyXRIwh7M8ccEqOqYvIzoM04=","PropertyOverridesHash":"8ZRc1sGeVrPBx4lD717BgRaQekyh78QKV9SKsdt638U=","InputHashes":["yLydHIiqaRuqDQOq9aJiDWuOlo41Ysc4i0qz3sAHvso=","Zl91Qs1cGRLXjP4hjSA53XQG9KTcE9g2\u002B8frQeeek7g="],"CachedAssets":{"yLydHIiqaRuqDQOq9aJiDWuOlo41Ysc4i0qz3sAHvso=":{"Identity":"C:\\Users\\Ronak\\Downloads\\TatvaSoft-Virtual-Community-Support-main\\Backend\\Mission.Api\\wwwroot\\Images\\N-tier Architecture.drawio_20250708065951.png","SourceId":"Mission.Api","SourceType":"Discovered","ContentRoot":"C:\\Users\\Ronak\\Downloads\\TatvaSoft-Virtual-Community-Support-main\\Backend\\Mission.Api\\wwwroot\\","BasePath":"_content/Mission.Api","RelativePath":"Images/N-tier Architecture.drawio_20250708065951#[.{fingerprint}]?.png","AssetKind":"All","AssetMode":"All","AssetRole":"Primary","AssetMergeBehavior":null,"AssetMergeSource":"","RelatedAsset":null,"AssetTraitName":null,"AssetTraitValue":null,"Fingerprint":"nz23l10vig","Integrity":"HTX9nq\u002B5RBb6z3pDA9fZB\u002Bde98ehWbzEDKE0LX3eows=","CopyToOutputDirectory":"Never","CopyToPublishDirectory":"PreserveNewest","OriginalItemSpec":"wwwroot\\Images\\N-tier Architecture.drawio_20250708065951.png","FileLength":37529,"LastWriteTime":"2025-07-15T05:43:21.9634597+00:00"}},"CachedCopyCandidates":{}}